belqis/__init__.py
belqis/belqis.py
belqis/clients.py
belqis-0.0.2.dist-info/LICENSE
belqis-0.0.2.dist-info/METADATA
belqis-0.0.2.dist-info/WHEEL
belqis-0.0.2.dist-info/top_level.txt
belqis-0.0.2.dist-info/RECORD
