Metadata-Version: 2.1
Name: belqis
Version: 0.0.2
Summary: A python client for Belqis System
Home-page: https://github.com/ahmedkhorsi/pybelqis
Author: Ahmed Khorsi
Author-email: ahmedkhorsi18@gmail.com
License: UNKNOWN
Platform: UNKNOWN
Classifier: Programming Language :: Python :: 3
Classifier: License :: OSI Approved :: MIT License
Classifier: Operating System :: OS Independent
Requires-Python: >=3.6
